{"@class": "de.fau.cs.inf2.cthree.data.Cluster", "id": "ad70cc7f90fbba258ac12c3eff067b40", "detectedBy": ["DIFF_HIERARCHICAL", "DIFF_DBSCAN", "AST_DBSCAN"], "members": [{"@class": "de.fau.cs.inf2.cthree.data.CodeChange", "id": "8dc703b384f31358521e7153939cc51e", "repository": "https://github.com/checkstyle/checkstyle.git", "fileName": "src/checkstyle/com/puppycrawl/tools/checkstyle/checks/annotation/MissingDeprecatedCheck.java", "commitBeforeChange": "d868a951ca1bdd8a6313fe10820bc9140ea030ff", "commitAfterChange": "fdc81723bdfd6af2ffc2c901cd8dd5b2fe948267", "methodNumberBeforeChange": 2, "methodNumberAfterChange": 2, "signatureBeforeChange": "\r     @Override\r     public void visitToken(final DetailAST aAST)", "signatureAfterChange": "\r     @Override\r     public void visitToken(final DetailAST aAST)", "diff": ["-            AnnotationUtility.containsAnnotation(aAST, DEPRECATED);\r", "+            AnnotationUtility.containsAnnotation(aAST, DEPRECATED)\r", "+            || AnnotationUtility.containsAnnotation(aAST, FQ_DEPRECATED);\r"]}, {"@class": "de.fau.cs.inf2.cthree.data.CodeChange", "id": "db079271c463f818f94b73ab4061c53b", "repository": "https://github.com/checkstyle/checkstyle.git", "fileName": "src/checkstyle/com/puppycrawl/tools/checkstyle/checks/annotation/MissingOverrideCheck.java", "commitBeforeChange": "d868a951ca1bdd8a6313fe10820bc9140ea030ff", "commitAfterChange": "fdc81723bdfd6af2ffc2c901cd8dd5b2fe948267", "methodNumberBeforeChange": 4, "methodNumberAfterChange": 4, "signatureBeforeChange": "\r     @Override\r     public void visitToken(final DetailAST aAST)", "signatureAfterChange": "\r     @Override\r     public void visitToken(final DetailAST aAST)", "diff": ["-            && !AnnotationUtility.containsAnnotation(aAST, OVERRIDE))\r", "+            && (!AnnotationUtility.containsAnnotation(aAST, OVERRIDE)\r", "+            && !AnnotationUtility.containsAnnotation(aAST, FQ_OVERRIDE)))\r"]}]}