{"@class": "de.fau.cs.inf2.cthree.data.Cluster", "id": "94128aa0122379ca658afcbfdaa3f3f7", "detectedBy": ["AST_HIERARCHICAL"], "members": [{"@class": "de.fau.cs.inf2.cthree.data.CodeChange", "id": "0f8fb078d99a3c502c876a226ee1e94b", "repository": "http://git.eclipse.org/gitroot/platform/eclipse.platform.swt.git", "fileName": "bundles/org.eclipse.swt/Eclipse SWT/cocoa/org/eclipse/swt/widgets/MenuItem.java", "commitBeforeChange": "853bd44cd4a1341872b64e8f30700a9b8502bcb3", "commitAfterChange": "c80d1a4367bae24d3c4c28fd4ddde731940ae8da", "methodNumberBeforeChange": 27, "methodNumberAfterChange": 27, "signatureBeforeChange": " public void setAccelerator (int accelerator)", "signatureAfterChange": " public void setAccelerator (int accelerator)", "diff": ["-\tnsItem.setHidden (false);", "-\tif ((this.accelerator == 0 && accelerator != 0) || (this.accelerator != 0 && accelerator == 0)) {", "-\t\tupdateText ();", "-\t}"]}, {"@class": "de.fau.cs.inf2.cthree.data.CodeChange", "id": "2a56730afbba9050010707b299551f23", "repository": "http://git.eclipse.org/gitroot/platform/eclipse.platform.swt.git", "fileName": "bundles/org.eclipse.swt/Eclipse SWT/win32/org/eclipse/swt/graphics/GC.java", "commitBeforeChange": "70e248bf5ea827d3db067893f71e76d06f5846cf", "commitAfterChange": "554c00a18df0d0c1a87f83c614fa4bb098dc894f", "methodNumberBeforeChange": 87, "methodNumberAfterChange": 87, "signatureBeforeChange": "  void setClipping(int clipRgn)", "signatureAfterChange": "  void setClipping(int clipRgn)", "diff": ["-\t\t\tif (pt.x != 0 || pt.y != 0) OS.OffsetRgn (hRgn, -pt.x, -pt.y);", "+\t\t\tOS.OffsetRgn (hRgn, -pt.x, -pt.y);", "-\t\tif (hRgn != 0 && (pt.x != 0 || pt.y != 0)) OS.OffsetRgn (hRgn, pt.x, pt.y);", "+\t\tif (hRgn != 0) OS.OffsetRgn (hRgn, pt.x, pt.y);"]}], "num": 60429}