{"@class": "de.fau.cs.inf2.cthree.data.Cluster", "id": "de0ab2815fca53dfd64267cbbfea3b84", "detectedBy": ["DIFF_DBSCAN"], "members": [{"@class": "de.fau.cs.inf2.cthree.data.CodeChange", "id": "4cd64d84f127f715185ce679a5247c74", "repository": "http://git.eclipse.org/gitroot/jdt/eclipse.jdt.core.git", "fileName": "org.eclipse.jdt.core.tests.model/src/org/eclipse/jdt/core/tests/model/AttachedJavadocTests.java", "commitBeforeChange": "e23731bfbef54b7b257bcd8302a58a01db83c05d", "commitAfterChange": "279ae109d40885f5a16be9af1d602322e1395a9b", "methodNumberBeforeChange": 30, "methodNumberAfterChange": 30, "signatureBeforeChange": " \tpublic void testBug304394() throws Exception", "signatureAfterChange": " \tpublic void testBug304394() throws Exception", "diff": ["-\t\t\tsavedEntries = (IClasspathEntry[]) entries.clone();", "+\t\t\tsavedEntries = entries.clone();"]}, {"@class": "de.fau.cs.inf2.cthree.data.CodeChange", "id": "7316c7854798f08df362a30431a53cdc", "repository": "http://git.eclipse.org/gitroot/jdt/eclipse.jdt.core.git", "fileName": "org.eclipse.jdt.core.tests.model/src/org/eclipse/jdt/core/tests/model/AttachedJavadocTests.java", "commitBeforeChange": "e23731bfbef54b7b257bcd8302a58a01db83c05d", "commitAfterChange": "279ae109d40885f5a16be9af1d602322e1395a9b", "methodNumberBeforeChange": 31, "methodNumberAfterChange": 31, "signatureBeforeChange": " \tpublic void testBug304394a() throws Exception", "signatureAfterChange": " \tpublic void testBug304394a() throws Exception", "diff": ["-\t\t\tsavedEntries = (IClasspathEntry[]) entries.clone();", "+\t\t\tsavedEntries = entries.clone();"]}], "num": 47705}