{"@class": "de.fau.cs.inf2.cthree.data.Cluster", "id": "9dd5b729626280050365141c80f3b85e", "detectedBy": ["AST_HIERARCHICAL", "AST_DBSCAN"], "members": [{"@class": "de.fau.cs.inf2.cthree.data.CodeChange", "id": "8b2878cf3844b06a367936ee6454998a", "repository": "http://git.eclipse.org/gitroot/platform/eclipse.platform.swt.git", "fileName": "bundles/org.eclipse.swt/Eclipse SWT Mozilla/cocoa/org/eclipse/swt/browser/MozillaDelegate.java", "commitBeforeChange": "4edc576de20a88abac088ae701d29ce3e54ede4f", "commitAfterChange": "c2ec875b36ecf39df432358c14d183b7d7f45fe0", "methodNumberBeforeChange": 2, "methodNumberAfterChange": 2, "signatureBeforeChange": "  static char[] mbcsToWcs (String codePage, byte [] buffer)", "signatureAfterChange": "  static char[] mbcsToWcs (String codePage, byte [] buffer)", "diff": ["-\tint encoding = OS.CFStringGetSystemEncoding ();", "-\tint cfstring = OS.CFStringCreateWithBytes (OS.kCFAllocatorDefault, buffer, buffer.length, encoding, false);", "-\tchar[] chars = null;", "-\tif (cfstring != 0) {", "-\t\tint length = OS.CFStringGetLength (cfstring);", "-\t\tchars = new char [length];", "-\t\tif (length != 0) {", "-\t\t\tCFRange range = new CFRange ();", "-\t\t\trange.length = length;", "-\t\t\tOS.CFStringGetCharacters (cfstring, range, chars);", "-\t\t}", "-\t\tOS.CFRelease (cfstring);", "-\t}", "-\treturn chars;", "+//\tint encoding = OS.CFStringGetSystemEncoding ();", "+//\tint cfstring = OS.CFStringCreateWithBytes (OS.kCFAllocatorDefault, buffer, buffer.length, encoding, false);", "+//\tchar[] chars = null;", "+//\tif (cfstring != 0) {", "+//\t\tint length = OS.CFStringGetLength (cfstring);", "+//\t\tchars = new char [length];", "+//\t\tif (length != 0) {", "+//\t\t\tCFRange range = new CFRange ();", "+//\t\t\trange.length = length;", "+//\t\t\tOS.CFStringGetCharacters (cfstring, range, chars);", "+//\t\t}", "+//\t\tOS.CFRelease (cfstring);", "+//\t}", "+//\treturn chars;", "+\treturn new String(buffer).toCharArray();"]}, {"@class": "de.fau.cs.inf2.cthree.data.CodeChange", "id": "a5267981ee21fbe0f5ba3822aa62583d", "repository": "http://git.eclipse.org/gitroot/platform/eclipse.platform.swt.git", "fileName": "bundles/org.eclipse.swt/Eclipse SWT/carbon/org/eclipse/swt/widgets/Text.java", "commitBeforeChange": "d8ec5bd674c9f38b94baa468b59c96ddbe13d4b5", "commitAfterChange": "116292d1bed8e86a80cf388e9d681c8e8491ddde", "methodNumberBeforeChange": 22, "methodNumberAfterChange": 22, "signatureBeforeChange": "  String getClipboardText()", "signatureAfterChange": "  String getClipboardText()", "diff": ["-\tif (OS.GetScrapFlavorSize (scrap [0], OS.kScrapFlavorTypeText, size) != OS.noErr || size [0] == 0) return \"\";", "-\tbyte [] buffer = new byte [size [0]];", "-\tif (OS.GetScrapFlavorData (scrap [0], OS.kScrapFlavorTypeText, size, buffer) != OS.noErr) return \"\";", "-\tint encoding = OS.CFStringGetSystemEncoding ();", "-\tint cfstring = OS.CFStringCreateWithBytes (OS.kCFAllocatorDefault, buffer, buffer.length, encoding, true);", "-\tif (cfstring == 0) return \"\";", "-\tString string = \"\";", "-\tint length = OS.CFStringGetLength (cfstring);", "-\tif (length != 0) {", "-\t\tchar [] chars = new char [length];", "-\t\tCFRange range = new CFRange ();", "-\t\trange.length = length;", "-\t\tOS.CFStringGetCharacters (cfstring, range, chars);", "-\t\tstring = new String (chars);", "-\t}", "-\tOS.CFRelease(cfstring);", "-\treturn string;", "+\tif (OS.GetScrapFlavorSize (scrap [0], OS.kScrapFlavorTypeUnicode, size) != OS.noErr || size [0] == 0) return \"\";", "+\tchar [] buffer = new char [size [0] / 2];", "+\tif (OS.GetScrapFlavorData (scrap [0], OS.kScrapFlavorTypeUnicode, size, buffer) != OS.noErr) return \"\";", "+\treturn new String (buffer);"]}], "num": 39035}