{"@class": "de.fau.cs.inf2.cthree.data.Cluster", "id": "49c3bff332203430196feb062b886dad", "detectedBy": ["DIFF_DBSCAN"], "members": [{"@class": "de.fau.cs.inf2.cthree.data.CodeChange", "id": "2a060af9b3d535e601c8163527281db5", "repository": "http://git.eclipse.org/gitroot/jdt/eclipse.jdt.core.git", "fileName": "org.eclipse.jdt.core/dom/org/eclipse/jdt/core/dom/LabeledStatement.java", "commitBeforeChange": "c8b5ecf7644442cf6b61e3ae0b667b7e3c5a788b", "commitAfterChange": "38b81cceafabaca157320ce2793e74f4a9686fd7", "methodNumberBeforeChange": 11, "methodNumberAfterChange": 11, "signatureBeforeChange": "  \tpublic void setBody(Statement statement)", "signatureAfterChange": "  \tpublic void setBody(Statement statement)", "diff": ["-\t\tpreReplaceChild(this.body, statement, BODY_PROPERTY);", "+\t\tASTNode oldChild = this.body;", "+\t\tpreReplaceChild(oldChild, statement, BODY_PROPERTY);", "-\t\tpostReplaceChild(this.body, statement, BODY_PROPERTY);", "+\t\tpostReplaceChild(oldChild, statement, BODY_PROPERTY);"]}, {"@class": "de.fau.cs.inf2.cthree.data.CodeChange", "id": "3e177f5ff835e7e74b0815c72e06399f", "repository": "http://git.eclipse.org/gitroot/jdt/eclipse.jdt.core.git", "fileName": "org.eclipse.jdt.core/dom/org/eclipse/jdt/core/dom/ForStatement.java", "commitBeforeChange": "c8b5ecf7644442cf6b61e3ae0b667b7e3c5a788b", "commitAfterChange": "38b81cceafabaca157320ce2793e74f4a9686fd7", "methodNumberBeforeChange": 14, "methodNumberAfterChange": 14, "signatureBeforeChange": "  \tpublic void setBody(Statement statement)", "signatureAfterChange": "  \tpublic void setBody(Statement statement)", "diff": ["-\t\tpreReplaceChild(this.body, statement, BODY_PROPERTY);", "+\t\tASTNode oldChild = this.body;", "+\t\tpreReplaceChild(oldChild, statement, BODY_PROPERTY);", "-\t\tpostReplaceChild(this.body, statement, BODY_PROPERTY);", "+\t\tpostReplaceChild(oldChild, statement, BODY_PROPERTY);"]}, {"@class": "de.fau.cs.inf2.cthree.data.CodeChange", "id": "d214acb325d107c2aede9fbc924eba65", "repository": "http://git.eclipse.org/gitroot/jdt/eclipse.jdt.core.git", "fileName": "org.eclipse.jdt.core/dom/org/eclipse/jdt/core/dom/EnhancedForStatement.java", "commitBeforeChange": "c8b5ecf7644442cf6b61e3ae0b667b7e3c5a788b", "commitAfterChange": "38b81cceafabaca157320ce2793e74f4a9686fd7", "methodNumberBeforeChange": 13, "methodNumberAfterChange": 13, "signatureBeforeChange": "  \tpublic void setBody(Statement statement)", "signatureAfterChange": "  \tpublic void setBody(Statement statement)", "diff": ["-\t\tpreReplaceChild(this.body, statement, BODY_PROPERTY);", "+\t\tASTNode oldChild = this.body;", "+\t\tpreReplaceChild(oldChild, statement, BODY_PROPERTY);", "-\t\tpostReplaceChild(this.body, statement, BODY_PROPERTY);", "+\t\tpostReplaceChild(oldChild, statement, BODY_PROPERTY);"]}], "num": 10995}