{"@class": "de.fau.cs.inf2.cthree.data.Cluster", "id": "4233c1036b7e92218aaf39e8f9e8ed8a", "detectedBy": ["DIFF_DBSCAN"], "members": [{"@class": "de.fau.cs.inf2.cthree.data.CodeChange", "id": "33502c6bb281c425964e4117c08ba99d", "repository": "http://git.eclipse.org/gitroot/jdt/eclipse.jdt.core.git", "fileName": "org.eclipse.jdt.core.tests.compiler/src/org/eclipse/jdt/core/tests/compiler/regression/AnnotationTest.java", "commitBeforeChange": "232201d6380e7830296a82a7b3422a333db36b2e", "commitAfterChange": "378f419edc5509790bbfa3083244109f6abafbe2", "methodNumberBeforeChange": 150, "methodNumberAfterChange": 150, "signatureBeforeChange": " public void test143()", "signatureAfterChange": " public void test143()", "diff": ["-\t\t\"\t                       ^^^^^^^^^^\\n\" +", "+\t\t\"\t                         ^^^^^^^^\\n\" +"]}, {"@class": "de.fau.cs.inf2.cthree.data.CodeChange", "id": "c2bcfdf81f9f7e82573b3df1f6515b58", "repository": "http://git.eclipse.org/gitroot/jdt/eclipse.jdt.core.git", "fileName": "org.eclipse.jdt.core.tests.compiler/src/org/eclipse/jdt/core/tests/compiler/regression/ExpressionContextTests.java", "commitBeforeChange": "8a281cea306104e13dc5d8e2e915592f13b4b03f", "commitAfterChange": "4f6e7772e1eab66068e8d31851a8e395b8beb754", "methodNumberBeforeChange": 5, "methodNumberAfterChange": 5, "signatureBeforeChange": " public void test003()", "signatureAfterChange": " public void test003()", "diff": ["-\t\t\t\"\t                         ^^^^^^^^\\n\" + ", "+\t\t\t\"\t                         ^^^^^\\n\" +"]}], "num": 29180}