{"@class": "de.fau.cs.inf2.cthree.data.Cluster", "id": "fec8005d61e4aeb21ea9b366c84d2da2", "detectedBy": ["DIFF_DBSCAN"], "members": [{"@class": "de.fau.cs.inf2.cthree.data.CodeChange", "id": "7ffa6175f791a2e6eacc443b3f7ba9bb", "repository": "http://git.eclipse.org/gitroot/platform/eclipse.platform.swt.git", "fileName": "bundles/org.eclipse.swt/Eclipse SWT Accessibility/gtk/org/eclipse/swt/accessibility/AccessibleObject.java", "commitBeforeChange": "3e57ee0ed42c71cf5b75eff6d71364caee02a643", "commitAfterChange": "bb3534bcdc2d38bc184b055b59a542f294cf921d", "methodNumberBeforeChange": 87, "methodNumberAfterChange": 88, "signatureBeforeChange": " \tstatic long atkValue_get_current_value (long atkObject, long value)", "signatureAfterChange": " \tstatic long atkValue_get_current_value (long atkObject, long value)", "diff": ["-\t\t\tint length = listeners.size();", "+\t\t\tint length = size(listeners);"]}, {"@class": "de.fau.cs.inf2.cthree.data.CodeChange", "id": "b045361a1004c7f77f0ae781d249e981", "repository": "http://git.eclipse.org/gitroot/platform/eclipse.platform.swt.git", "fileName": "bundles/org.eclipse.swt/Eclipse SWT Accessibility/gtk/org/eclipse/swt/accessibility/AccessibleObject.java", "commitBeforeChange": "3e57ee0ed42c71cf5b75eff6d71364caee02a643", "commitAfterChange": "bb3534bcdc2d38bc184b055b59a542f294cf921d", "methodNumberBeforeChange": 20, "methodNumberAfterChange": 21, "signatureBeforeChange": " \tstatic long atkEditableText_delete_text (long atkObject, long start_pos, long end_pos)", "signatureAfterChange": " \tstatic long atkEditableText_delete_text (long atkObject, long start_pos, long end_pos)", "diff": ["-\t\t\tint length = listeners.size();", "+\t\t\tint length = size(listeners);"]}, {"@class": "de.fau.cs.inf2.cthree.data.CodeChange", "id": "e91b20abd8ea9288191779eefb4139b4", "repository": "http://git.eclipse.org/gitroot/platform/eclipse.platform.swt.git", "fileName": "bundles/org.eclipse.swt/Eclipse SWT Accessibility/gtk/org/eclipse/swt/accessibility/AccessibleObject.java", "commitBeforeChange": "3e57ee0ed42c71cf5b75eff6d71364caee02a643", "commitAfterChange": "bb3534bcdc2d38bc184b055b59a542f294cf921d", "methodNumberBeforeChange": 60, "methodNumberAfterChange": 61, "signatureBeforeChange": "  \tstatic long atkTable_remove_row_selection (long atkObject, long row)", "signatureAfterChange": "  \tstatic long atkTable_remove_row_selection (long atkObject, long row)", "diff": ["-\t\t\tint length = listeners.size();", "+\t\t\tint length = size(listeners);"]}, {"@class": "de.fau.cs.inf2.cthree.data.CodeChange", "id": "cacb33f91291f47470d16ad6c6f05886", "repository": "http://git.eclipse.org/gitroot/platform/eclipse.platform.swt.git", "fileName": "bundles/org.eclipse.swt/Eclipse SWT Accessibility/gtk/org/eclipse/swt/accessibility/AccessibleObject.java", "commitBeforeChange": "3e57ee0ed42c71cf5b75eff6d71364caee02a643", "commitAfterChange": "bb3534bcdc2d38bc184b055b59a542f294cf921d", "methodNumberBeforeChange": 11, "methodNumberAfterChange": 12, "signatureBeforeChange": "  \tstatic long atkComponent_get_size (long atkObject, long width, long height, long coord_type)", "signatureAfterChange": "  \tstatic long atkComponent_get_size (long atkObject, long width, long height, long coord_type)", "diff": ["-\t\t\tint length = listeners.size();", "+\t\t\tint length = size(listeners);"]}], "num": 56498}