{"@class": "de.fau.cs.inf2.cthree.data.Cluster", "id": "ce198b4164599f8f1d53efd3705a6e00", "detectedBy": ["DIFF_DBSCAN"], "members": [{"@class": "de.fau.cs.inf2.cthree.data.CodeChange", "id": "95ef7c2fbb7f30c156a3340ac65037f0", "repository": "http://git.eclipse.org/gitroot/platform/eclipse.platform.swt.git", "fileName": "bundles/org.eclipse.swt/Eclipse SWT/cocoa/org/eclipse/swt/widgets/Table.java", "commitBeforeChange": "b4a2320440164ae72ce51dd2342d464a54f498b9", "commitAfterChange": "84656a6e6ceb9594f856cbee82c381105c177330", "methodNumberBeforeChange": 10, "methodNumberAfterChange": 10, "signatureBeforeChange": "  public Point computeSize (int wHint, int hHint, boolean changed)", "signatureAfterChange": "  public Point computeSize (int wHint, int hHint, boolean changed)", "diff": ["-//\t\tif ((style & SWT.CHECK) != 0) width += getCheckColumnWidth ();", "+\t\tif ((style & SWT.CHECK) != 0) width += getCheckColumnWidth ();"]}, {"@class": "de.fau.cs.inf2.cthree.data.CodeChange", "id": "0245818c6bc57f16476b3fedc1bb91cb", "repository": "http://git.eclipse.org/gitroot/platform/eclipse.platform.swt.git", "fileName": "bundles/org.eclipse.swt/Eclipse SWT/win32/org/eclipse/swt/widgets/Table.java", "commitBeforeChange": "9f800048edf52ed70457895b32ddfeee108ffda8", "commitAfterChange": "90ba9cb2ff16ee7ec96ab5262879eb4d4ffb3bc7", "methodNumberBeforeChange": 2, "methodNumberAfterChange": 2, "signatureBeforeChange": "  void _setBackgroundImage (Image image)", "signatureAfterChange": "  void _setBackgroundImage (Image image)", "diff": ["-\t\t\tif ((style & SWT.CHECK) != 0) setCheckboxImageListColor ();", "+\t\t\tif ((style & SWT.CHECK) != 0) fixCheckboxImageListColor (true);"]}], "num": 17563}