{"@class": "de.fau.cs.inf2.cthree.data.Cluster", "id": "b7bd39f8c1f97347ef528a912086d6fe", "detectedBy": ["DIFF_DBSCAN"], "members": [{"@class": "de.fau.cs.inf2.cthree.data.CodeChange", "id": "06d7eafa0d8c7c2eb93720a95f729ee4", "repository": "http://git.code.sf.net/p/drjava/git_repo", "fileName": "drjava/src/edu/rice/cs/drjava/ui/MainFrame.java", "commitBeforeChange": "d0727a77251489c271609794ef5d58d9b3aab593", "commitAfterChange": "e782d4da2d7bff038017015047af677bda357a17", "methodNumberBeforeChange": 157, "methodNumberAfterChange": 159, "signatureBeforeChange": "          public void breakpointRemoved(final Breakpoint bp)", "signatureAfterChange": "          public void breakpointRemoved(final Breakpoint bp)", "diff": ["-      highlight.remove();", "+      if (highlight != null) highlight.remove();"]}, {"@class": "de.fau.cs.inf2.cthree.data.CodeChange", "id": "7886baf879767daeec4d365382ca12df", "repository": "http://git.code.sf.net/p/drjava/git_repo", "fileName": "drjava/src/edu/rice/cs/drjava/config/PropertyMaps.java", "commitBeforeChange": "bd115d85e858b9ca09ebbbacbcf2bcab93ec2746", "commitAfterChange": "74f91d4ab1bc60eb8b5e8fd35cfb982ee9101049", "methodNumberBeforeChange": 13, "methodNumberAfterChange": 13, "signatureBeforeChange": "   public void removeVariable(String name)", "signatureAfterChange": "   public void removeVariable(String name)", "diff": ["-      _variables.remove(varStack);", "+      _variables.remove(name);"]}], "num": 1374}