{"@class": "de.fau.cs.inf2.cthree.data.Cluster", "id": "33b253a010950df172341d346fae0f2a", "detectedBy": ["DIFF_HIERARCHICAL"], "members": [{"@class": "de.fau.cs.inf2.cthree.data.CodeChange", "id": "c2000594c7e77bcb7d90c9b0681167da", "repository": "http://git.eclipse.org/gitroot/jdt/eclipse.jdt.core.git", "fileName": "org.eclipse.jdt.core/model/org/eclipse/jdt/internal/core/CopyPackageFragmentRootOperation.java", "commitBeforeChange": "c15068401ccbe5d70df62cefab3f9cdf1587a7e9", "commitAfterChange": "0996c059ca3df90eb34cc804b74630022243a6c1", "methodNumberBeforeChange": 5, "methodNumberAfterChange": 5, "signatureBeforeChange": " \tprotected IClasspathEntry copy(IClasspathEntry entry) throws JavaModelException", "signatureAfterChange": " \tprotected IClasspathEntry copy(IClasspathEntry entry) throws JavaModelException", "diff": ["-\t\t\t\t} catch (Assert.AssertionFailedException e) {", "+\t\t\t\t} catch (AssertionFailedException e) {", "-\t\t\t\t} catch (Assert.AssertionFailedException e) {", "+\t\t\t\t} catch (AssertionFailedException e) {"]}, {"@class": "de.fau.cs.inf2.cthree.data.CodeChange", "id": "e5cfddf9e57bb03e58d1398219d07fad", "repository": "http://git.eclipse.org/gitroot/jdt/eclipse.jdt.core.git", "fileName": "org.eclipse.jdt.core/model/org/eclipse/jdt/internal/core/CopyPackageFragmentRootOperation.java", "commitBeforeChange": "aa1c17694b27b504666c5ba8972f5deebf077d85", "commitAfterChange": "26ddee9495db90c29b250e3eed03a94e2269259d", "methodNumberBeforeChange": 5, "methodNumberAfterChange": 5, "signatureBeforeChange": " \tprotected IClasspathEntry copy(IClasspathEntry entry) throws JavaModelException", "signatureAfterChange": " \tprotected IClasspathEntry copy(IClasspathEntry entry) throws JavaModelException", "diff": ["-\t\t\t\t} catch (AssertionFailedException e) {", "+\t\t\t\t} catch (ClasspathEntry.AssertionFailedException e) {", "-\t\t\t\t} catch (AssertionFailedException e) {", "+\t\t\t\t} catch (ClasspathEntry.AssertionFailedException e) {"]}], "num": 48114}