{"@class": "de.fau.cs.inf2.cthree.data.Cluster", "id": "e04e09bc3e1894bc296af3d310a0d66c", "detectedBy": ["AST_DBSCAN"], "members": [{"@class": "de.fau.cs.inf2.cthree.data.CodeChange", "id": "0d3f8c172a033edadcf4013e6b1fd97a", "repository": "http://git.eclipse.org/gitroot/platform/eclipse.platform.swt.git", "fileName": "bundles/org.eclipse.swt/Eclipse SWT/gtk/org/eclipse/swt/widgets/Control.java", "commitBeforeChange": "bc8036435837353efa5da8c19b6a3003dbb86045", "commitAfterChange": "5721cfd149c1026b4c21848f64c2b57027ac8c7e", "methodNumberBeforeChange": 4, "methodNumberAfterChange": 4, "signatureBeforeChange": "  void drawBackground (Control control, int window, int region, int x, int y, int width, int height)", "signatureAfterChange": "  void drawBackground (Control control, long window, long region, int x, int y, int width, int height)", "diff": ["-void drawBackground (Control control, int /*long*/ window, int /*long*/ region, int x, int y, int width, int height) {", "+void drawBackground (Control control, long /*int*/ window, long /*int*/ region, int x, int y, int width, int height) {", "-\t\tint /*long*/ cairo = OS.gdk_cairo_create(window);", "+\t\tlong /*int*/ cairo = OS.gdk_cairo_create(window);", "-\t\t\tint /*long*/ pattern = Cairo.cairo_pattern_create_for_surface (control.backgroundImage.surface);", "+\t\t\tlong /*int*/ pattern = Cairo.cairo_pattern_create_for_surface (control.backgroundImage.surface);", "-\tint /*long*/ gdkGC = OS.gdk_gc_new (window);", "+\tlong /*int*/ gdkGC = OS.gdk_gc_new (window);"]}, {"@class": "de.fau.cs.inf2.cthree.data.CodeChange", "id": "19a130e2c0165e370d028cdf76b3cbea", "repository": "http://git.eclipse.org/gitroot/platform/eclipse.platform.swt.git", "fileName": "bundles/org.eclipse.swt/Eclipse SWT OLE Win32/win32/org/eclipse/swt/ole/win32/OleFrame.java", "commitBeforeChange": "bc8036435837353efa5da8c19b6a3003dbb86045", "commitAfterChange": "5721cfd149c1026b4c21848f64c2b57027ac8c7e", "methodNumberBeforeChange": 34, "methodNumberAfterChange": 34, "signatureBeforeChange": " private int InsertMenus(int hmenuShared, int lpMenuWidths)", "signatureAfterChange": " private int InsertMenus(long hmenuShared, long lpMenuWidths)", "diff": ["-private int InsertMenus(int /*long*/ hmenuShared, int /*long*/ lpMenuWidths) {", "+private int InsertMenus(long /*int*/ hmenuShared, long /*int*/ lpMenuWidths) {", "-\tint /*long*/ hMenu = menubar.handle;", "+\tlong /*int*/ hMenu = menubar.handle;", "-\tint /*long*/ hHeap = OS.GetProcessHeap();", "+\tlong /*int*/ hHeap = OS.GetProcessHeap();", "-\tint /*long*/ pszText = OS.HeapAlloc(hHeap, OS.HEAP_ZERO_MEMORY, byteCount);", "+\tlong /*int*/ pszText = OS.HeapAlloc(hHeap, OS.HEAP_ZERO_MEMORY, byteCount);"]}], "num": 19910}