{"@class": "de.fau.cs.inf2.cthree.data.Cluster", "id": "a1011297d4f728b35c059feee703c238", "detectedBy": ["DIFF_DBSCAN"], "members": [{"@class": "de.fau.cs.inf2.cthree.data.CodeChange", "id": "0a0baceb6b9587c3525cf8bd8fc0c49b", "repository": "https://github.com/checkstyle/checkstyle.git", "fileName": "src/checkstyle/com/puppycrawl/tools/checkstyle/LineText.java", "commitBeforeChange": "2279ec2a489d1104f2741f2aa3458857d862ac34", "commitAfterChange": "6970485b88600343de72af03a6bf87cf78e6cf55", "methodNumberBeforeChange": 0, "methodNumberAfterChange": 0, "signatureBeforeChange": "     LineText(int aLineNo, String aText)", "signatureAfterChange": "     LineText(int aLineNo, String aText)", "diff": ["+        this(aLineNo, 0, aText);", "+    }"]}, {"@class": "de.fau.cs.inf2.cthree.data.CodeChange", "id": "201006d6733ee9988a90b95356d1bc67", "repository": "https://github.com/checkstyle/checkstyle.git", "fileName": "src/checkstyle/com/puppycrawl/tools/checkstyle/Main.java", "commitBeforeChange": "1846dacad6c2a3a04b3350b45bb8b05835192296", "commitAfterChange": "dd477210aefeabb265e105a9fe8120c8310605e8", "methodNumberBeforeChange": 0, "methodNumberAfterChange": 0, "signatureBeforeChange": "     public static void main(String[] aArgs)", "signatureAfterChange": "     public static void main(String[] aArgs)", "diff": ["-        addCustomListeners(c, line);", "-    }"]}]}