{"@class": "de.fau.cs.inf2.cthree.data.Cluster", "id": "caa6e5c253d0aaa62fe1b345e0f2ca95", "detectedBy": ["DIFF_DBSCAN"], "members": [{"@class": "de.fau.cs.inf2.cthree.data.CodeChange", "id": "b243a6ab30db2b804c2030388114559e", "repository": "http://git.eclipse.org/gitroot/jdt/eclipse.jdt.core.git", "fileName": "org.eclipse.jdt.core/model/org/eclipse/jdt/internal/core/JavaElement.java", "commitBeforeChange": "73cb911baa8db75db819f7327ce2bb8d1c8537b4", "commitAfterChange": "8eb8a403023f2b292819a8553addbce778b506a6", "methodNumberBeforeChange": 26, "methodNumberAfterChange": 26, "signatureBeforeChange": "\r public Object getRawInfo() throws JavaModelException", "signatureAfterChange": "\r public Object getRawInfo() throws JavaModelException", "diff": ["-\tsynchronized(fgJavaModelManager){\r", "-\t\tObject info = fgJavaModelManager.getInfo(this);\r", "+\tsynchronized(JavaModelManager.getJavaModelManager()){\r", "+\t\tObject info = JavaModelManager.getJavaModelManager().getInfo(this);\r", "-\t\t\tinfo= fgJavaModelManager.getInfo(this);\r", "+\t\t\tinfo= JavaModelManager.getJavaModelManager().getInfo(this);\r"]}, {"@class": "de.fau.cs.inf2.cthree.data.CodeChange", "id": "e58d47b52ae94c2805e7904af447ca12", "repository": "http://git.eclipse.org/gitroot/jdt/eclipse.jdt.core.git", "fileName": "org.eclipse.jdt.core/model/org/eclipse/jdt/internal/core/JavaElement.java", "commitBeforeChange": "22e4a3a51dab58eac41eb2aeee987914d9aa2e95", "commitAfterChange": "f1d71cfca3ffb7ac112e114ead9ea1434be4f21e", "methodNumberBeforeChange": 13, "methodNumberAfterChange": 13, "signatureBeforeChange": "\r public JavaElementInfo getElementInfo() throws JavaModelException", "signatureAfterChange": "\r public JavaElementInfo getElementInfo() throws JavaModelException", "diff": ["-\tsynchronized(JavaModelManager.getJavaModelManager()){\r", "-\t\tObject info = JavaModelManager.getJavaModelManager().getInfo(this);\r", "+\tJavaModelManager manager;\r", "+\tsynchronized(manager = JavaModelManager.getJavaModelManager()){\r", "+\t\tObject info = manager.getInfo(this);\r", "-\t\t\tinfo= JavaModelManager.getJavaModelManager().getInfo(this);\r", "+\t\t\tinfo= manager.getInfo(this);\r"]}], "num": 19061}