{"@class": "de.fau.cs.inf2.cthree.data.Cluster", "id": "310b8e79a01626530253ecbfa19353a1", "detectedBy": ["DIFF_HIERARCHICAL", "DIFF_DBSCAN"], "members": [{"@class": "de.fau.cs.inf2.cthree.data.CodeChange", "id": "1b414db478ea2c43894f33735d07fb85", "repository": "http://git.eclipse.org/gitroot/jdt/eclipse.jdt.core.git", "fileName": "org.eclipse.jdt.core/eval/org/eclipse/jdt/internal/eval/CodeSnippetParser.java", "commitBeforeChange": "3aa835135283a2acadb61b0aae182c129f17ffab", "commitAfterChange": "a9c15bae1087a65c1bc60140ceb7a5a5416fd8a8", "methodNumberBeforeChange": 37, "methodNumberAfterChange": 37, "signatureBeforeChange": "\r protected boolean resumeOnSyntaxError()", "signatureAfterChange": "\r protected boolean resumeOnSyntaxError()", "diff": ["-\tthis.scanner.eofPosition = this.codeSnippetEnd + 1; // stop after expression \r", "+\tthis.scanner.eofPosition = this.codeSnippetEnd < Integer.MAX_VALUE ? this.codeSnippetEnd + 1 : this.codeSnippetEnd; // stop after expression \r"]}, {"@class": "de.fau.cs.inf2.cthree.data.CodeChange", "id": "318d4ff4169d097dd8b912dc38edc04b", "repository": "http://git.eclipse.org/gitroot/jdt/eclipse.jdt.core.git", "fileName": "org.eclipse.jdt.core/compiler/org/eclipse/jdt/internal/compiler/parser/Parser.java", "commitBeforeChange": "5b37648dead58e0f08eb29205d0792e2cc2d0ce3", "commitAfterChange": "a65695d6239a320c5706ff9541c953fbd7d4abb9", "methodNumberBeforeChange": 423, "methodNumberAfterChange": 423, "signatureBeforeChange": " protected void reportSyntaxErrors(boolean isDietParse, int oldFirstToken)", "signatureAfterChange": " protected void reportSyntaxErrors(boolean isDietParse, int oldFirstToken)", "diff": ["-\tint end = this.scanner.eofPosition <= Integer.MAX_VALUE ? this.scanner.eofPosition - 1 : this.scanner.eofPosition;", "+\tint end = this.scanner.eofPosition == Integer.MAX_VALUE ? this.scanner.eofPosition : this.scanner.eofPosition - 1;"]}], "num": 68642}