{"@class": "de.fau.cs.inf2.cthree.data.Cluster", "id": "7a12c05d0ca3585786770db291d92be4", "detectedBy": ["DIFF_DBSCAN"], "members": [{"@class": "de.fau.cs.inf2.cthree.data.CodeChange", "id": "87bea506ea0c58f604b3560dcd4e7ebe", "repository": "http://git.code.sf.net/p/drjava/git_repo", "fileName": "dynamicjava/src/koala/dynamicjava/parser/Parser.java", "commitBeforeChange": "1e89570173a057456dfaafaaf0fe0900c92c74a8", "commitAfterChange": "b24b0a9d39ea5edde092f4dd2f0cce709847f77c", "methodNumberBeforeChange": 119, "methodNumberAfterChange": 117, "signatureBeforeChange": "   final public List<Expression> argumentList() throws ParseException", "signatureAfterChange": "   final public List<Expression> argumentList() throws ParseException", "diff": ["-        jj_la1[115] = jj_gen;", "+        jj_la1[113] = jj_gen;"]}, {"@class": "de.fau.cs.inf2.cthree.data.CodeChange", "id": "a62628f5dc108656336847fdef925734", "repository": "http://git.code.sf.net/p/drjava/git_repo", "fileName": "dynamicjava/src/koala/dynamicjava/parser/Parser.java", "commitBeforeChange": "f86dda75531ffcea84892045ae81ebf50612eb98", "commitAfterChange": "8a127e29dd0d7227ac32633c7c5c2f5db2cf4853", "methodNumberBeforeChange": 110, "methodNumberAfterChange": 111, "signatureBeforeChange": "   final public ExpressionSuffix primarySuffix() throws ParseException", "signatureAfterChange": "   final public ExpressionSuffix primarySuffix() throws ParseException", "diff": ["-        jj_la1[110] = jj_gen;", "+        jj_la1[119] = jj_gen;"]}, {"@class": "de.fau.cs.inf2.cthree.data.CodeChange", "id": "f1f2b5f23cfb54fbdd853a2b69419580", "repository": "http://git.code.sf.net/p/drjava/git_repo", "fileName": "dynamicjava/src/koala/dynamicjava/parser/Parser.java", "commitBeforeChange": "b5c763bf27a5267e7ff6eb7560dbde820d19b063", "commitAfterChange": "0b7f9842c42a34509d077a5e1d655daf0b8192d6", "methodNumberBeforeChange": 100, "methodNumberAfterChange": 101, "signatureBeforeChange": "   final public Expression castExpression() throws ParseException", "signatureAfterChange": "   final public Expression castExpression() throws ParseException", "diff": ["-        jj_la1[114] = jj_gen;", "+        jj_la1[116] = jj_gen;"]}], "num": 17827}