{"@class": "de.fau.cs.inf2.cthree.data.Cluster", "id": "af2d5f8ae3dbaabc3cb3ec1f5e511a23", "detectedBy": ["AST_DBSCAN"], "members": [{"@class": "de.fau.cs.inf2.cthree.data.CodeChange", "id": "e834be91fc58eda30c200e5dfb5451d6", "repository": "https://git-wip-us.apache.org/repos/asf/ant.git", "fileName": "proposal/myrmidon/src/java/org/apache/ant/project/DefaultTarget.java", "commitBeforeChange": "c6a798ef68e969311121bbe219367ffcc01bc621", "commitAfterChange": "bba92ec2234c85ea1ff3ec3e4e2bb45adaaf3197", "methodNumberBeforeChange": 5, "methodNumberAfterChange": 1, "signatureBeforeChange": "      public void setIfCondition( final boolean isIfCondition )", "signatureAfterChange": "      public DefaultTarget()", "diff": ["+", "+    public DefaultTarget()", "+    {", "+        this( null );", "+    }", "-", "-    public void setIfCondition( final boolean isIfCondition )", "-    {", "-        m_isIfCondition = isIfCondition;"]}, {"@class": "de.fau.cs.inf2.cthree.data.CodeChange", "id": "f81e763edfb7cfda54b730e5bbd55883", "repository": "https://git-wip-us.apache.org/repos/asf/ant.git", "fileName": "src/main/org/apache/tools/ant/taskdefs/optional/dotnet/CSharp.java", "commitBeforeChange": "e5a85d7265ed5c9a0e391d5d00596368229e8014", "commitAfterChange": "620b8828e3694634896ff05057883da63211fc2f", "methodNumberBeforeChange": 1, "methodNumberAfterChange": 20, "signatureBeforeChange": "     public void setReferences(String s)", "signatureAfterChange": "     public String getReferenceDelimiter()", "diff": ["-     */", "-    public void setReferences(String s) {", "-        references = s;", "-    }", "+     */", "+    public String getReferenceDelimiter() {", "+        return \";\";", "+    }"]}]}