{"@class": "de.fau.cs.inf2.cthree.data.Cluster", "id": "db384ebb0d255ade174c49269ecd9584", "detectedBy": ["AST_HIERARCHICAL"], "members": [{"@class": "de.fau.cs.inf2.cthree.data.CodeChange", "id": "f86bb82657088f26785860a79bb35bb6", "repository": "http://git.eclipse.org/gitroot/platform/eclipse.platform.swt.git", "fileName": "bundles/org.eclipse.swt/Eclipse SWT/carbon/org/eclipse/swt/graphics/GC.java", "commitBeforeChange": "d6b025633a28920ae40301a1b987f0b923d26e74", "commitAfterChange": "6e89f26f4d6cf8c990840a7f12e701138a427091", "methodNumberBeforeChange": 66, "methodNumberAfterChange": 66, "signatureBeforeChange": "  \tprivate void unfocus(boolean clip)", "signatureAfterChange": "  \tprivate void unfocus(boolean doClip)", "diff": ["+", "+\tprivate void unfocus(boolean doClip) {", "-", "-\tprivate void unfocus(boolean clip) {", "-\t\tif (! fIsFocused) {", "-\t\t\tif (clip) {", "-\t\t\t\t// restore clipping and origin of port", "-\t\t\t\tOS.SetClip(fSaveClip);", "-\t\t\t\tOS.SetOrigin((short)0, (short)0);", "-\t\t\t}", "+\t\tif (doClip) {", "+\t\t\t// restore clipping and origin of port", "+\t\t\tOS.SetClip(fSaveClip);", "+\t\t\tOS.SetOrigin((short)0, (short)0);"]}, {"@class": "de.fau.cs.inf2.cthree.data.CodeChange", "id": "c4a51230e61d6e3143256b9bf7e6e796", "repository": "http://git.eclipse.org/gitroot/platform/eclipse.platform.swt.git", "fileName": "bundles/org.eclipse.swt/Eclipse SWT/carbon/org/eclipse/swt/widgets/Shell.java", "commitBeforeChange": "9a79fbd85cda981978050b58fe5d23529aaf1f11", "commitAfterChange": "78583589ef78fe725513dd2adf8d72b6c314d56e", "methodNumberBeforeChange": 76, "methodNumberAfterChange": 76, "signatureBeforeChange": "  void setWindowVisible (boolean visible)", "signatureAfterChange": "  void setWindowVisible (boolean visible)", "diff": ["-\t\topened = true;", "-\t\tif (!moved) {", "-\t\t\tmoved = true;", "-\t\t\tsendEvent (SWT.Move);", "-\t\t\tif (isDisposed ()) return;", "-\t\t}", "-\t\tif (!resized) {", "-\t\t\tresized = true;", "-\t\t\tsendEvent (SWT.Resize);", "-\t\t\tif (isDisposed ()) return;", "-\t\t\tif (layout != null) {", "-\t\t\t\tmarkLayout (false, false);", "-\t\t\t\tupdateLayout (false);", "-\t\t\t}", "-\t\t}", "-\t\tif (!isDisposed()) {", "-\t\t\tif (minimized != OS.IsWindowCollapsed (shellHandle)) {", "-\t\t\t\tOS.CollapseWindow (shellHandle, minimized);", "-\t\t\t}", "-\t\t\tif ((style & SWT.ON_TOP) != 0) {", "-\t\t\t\tOS.SetWindowActivationScope (shellHandle, scope [0]);", "+\t\tif (isDisposed()) return;", "+\t\tif (minimized != OS.IsWindowCollapsed (shellHandle)) {", "+\t\t\tOS.CollapseWindow (shellHandle, minimized);", "+\t\t}", "+\t\tif ((style & SWT.ON_TOP) != 0) {", "+\t\t\tOS.SetWindowActivationScope (shellHandle, scope [0]);", "+\t\t}", "+\t\topened = true;", "+\t\tif (!moved) {", "+\t\t\tmoved = true;", "+\t\t\tsendEvent (SWT.Move);", "+\t\t\tif (isDisposed ()) return;", "+\t\t}", "+\t\tif (!resized) {", "+\t\t\tresized = true;", "+\t\t\tsendEvent (SWT.Resize);", "+\t\t\tif (isDisposed ()) return;", "+\t\t\tif (layout != null) {", "+\t\t\t\tmarkLayout (false, false);", "+\t\t\t\tupdateLayout (false);"]}], "num": 54372}