{"@class": "de.fau.cs.inf2.cthree.data.Cluster", "id": "2de59c37b3e5545a74be1810051c039a", "detectedBy": ["DIFF_DBSCAN"], "members": [{"@class": "de.fau.cs.inf2.cthree.data.CodeChange", "id": "4211b3a66e47cbbb2258726ec7988ba5", "repository": "http://git.eclipse.org/gitroot/jdt/eclipse.jdt.core.git", "fileName": "org.eclipse.jdt.core/model/org/eclipse/jdt/internal/core/DeltaProcessor.java", "commitBeforeChange": "d9cf56fd4fe99ad8dd0ba89cbfa9dcc246ef0b9c", "commitAfterChange": "c143533d344835eae9053a7d384648906ed40cff", "methodNumberBeforeChange": 8, "methodNumberAfterChange": 10, "signatureBeforeChange": " \tvoid addToProjectsToUpdateWithDependents(IProject project)", "signatureAfterChange": " \tprivate void addToRootsToRefreshWithDependents(IJavaProject javaProject)", "diff": ["-\t */", "-\tvoid addToProjectsToUpdateWithDependents(IProject project) {", "-\t\tthis.projectsToUpdate.add(JavaCore.create(project));", "-\t\tthis.addDependentProjects(project.getFullPath(), this.projectsToUpdate);", "-\t}", "+\t */", "+\tprivate void addToRootsToRefreshWithDependents(IJavaProject javaProject) {", "+\t\tthis.rootsToRefresh.add(javaProject);", "+\t\tthis.addDependentProjects(javaProject.getPath(), this.rootsToRefresh);", "+\t}"]}, {"@class": "de.fau.cs.inf2.cthree.data.CodeChange", "id": "d2abc81566b5a45a3d220481d2a06391", "repository": "http://git.eclipse.org/gitroot/jdt/eclipse.jdt.core.git", "fileName": "org.eclipse.jdt.core/model/org/eclipse/jdt/internal/core/DeltaProcessor.java", "commitBeforeChange": "5ec0d4f852b715851ad782798e616c99fb28d2e1", "commitAfterChange": "8a34d2aa53a9b1b6521aba520000cbaff6e630ff", "methodNumberBeforeChange": 13, "methodNumberAfterChange": 13, "signatureBeforeChange": "\r \tprotected void elementRemoved(Openable element, IResourceDelta delta)", "signatureAfterChange": "\r \tprotected void elementRemoved(Openable element, IResourceDelta delta)", "diff": ["-\t\t\t\tthis.projectsToUpdate.add(element.getJavaProject());\r", "+\t\t\t\tJavaProject project = (JavaProject) element.getJavaProject();\r", "+\t\t\t\tthis.projectsToUpdate.add(project);\r", "+\t\t\t\tthis.projectsForDependentNamelookupRefresh.add(project);\t\t\t\t\r", "-\t\t\t\tJavaProject project = (JavaProject) element.getJavaProject();\r", "+\t\t\t\tproject = (JavaProject) element.getJavaProject();\r", "+\t\t\t\t\tthis.projectsForDependentNamelookupRefresh.add(project);\r"]}], "num": 15773}